Metadata-Version: 2.1
Name: openexpressions
Version: 1.4
Summary: A easy to use and expandable expression parser
Home-page: https://github.com/AaryamanBhute/OpenExpressions
Download-URL: https://github.com/AaryamanBhute/OpenExpressions/v_10.tar.gz
Author: Aaryaman Bhute
Author-email: aryamanbhute@gmail.com
License: MIT
Keywords: EXPRESSION,PARSER,EXPANDABLE,CUSTOMIZABLE
Classifier: Development Status :: 4 - Beta
Classifier: Intended Audience :: Developers
Classifier: Topic :: Software Development :: Build Tools
Classifier: License :: OSI Approved :: MIT License
Classifier: Programming Language :: Python :: 3
Classifier: Programming Language :: Python :: 3.4
Classifier: Programming Language :: Python :: 3.5
Classifier: Programming Language :: Python :: 3.6
Classifier: Programming Language :: Python :: 3.7
Classifier: Programming Language :: Python :: 3.8
Classifier: Programming Language :: Python :: 3.9
Classifier: Programming Language :: Python :: 3.10
Classifier: Programming Language :: Python :: 3.11
License-File: LICENSE.txt
